{"speed": 12.0, "notes": [{"$id": 1, "sounds": [{"d": 0.333806753, "p": 72, "v": 93}], "pos": -1.0, "size": 1.0, "_time": 1.0234375}, {"$id": 2, "sounds": [{"d": 0.681818, "p": 67, "v": 70}, {"d": 0.681818, "p": 65, "v": 69}], "pos": -2.0, "size": 1.30000007, "_time": 1.35546875}, {"$id": 3, "sounds": [{"d": 0.681818, "p": 79, "v": 90}], "size": 1.0, "_time": 1.35546875, "pos": 0}, {"$id": 4, "sounds": [{"d": 0.553977251, "p": 79, "v": 89}], "size": 1.0, "_time": 2.0390625, "pos": 0}, {"$id": 5, "sounds": [{"d": 0.4616475, "p": 81, "v": 90}], "pos": 1.0, "size": 1.0, "_time": 2.59375}, {"$id": 6, "sounds": [{"d": 0.3551135, "p": 53, "v": 67}], "pos": -2.0, "size": 1.0, "_time": 3.0546875}, {"$id": 7, "sounds": [{"d": 0.333806753, "p": 65, "v": 68}], "pos": -1.0, "size": 1.0, "_time": 3.41015625}, {"$id": 8, "sounds": [{"d": 0.333806753, "p": 72, "v": 91}], "size": 1.0, "_time": 3.7421875, "pos": 0}, {"$id": 9, "sounds": [{"d": 0.6889205, "p": 79, "v": 89}], "pos": 1.0, "size": 1.0, "_time": 4.078125}, {"$id": 10, "sounds": [{"d": 0.6889205, "p": 72, "v": 72}, {"d": 0.6889205, "p": 75, "v": 73}, {"w": 0.00390625, "d": 0.681818, "p": 67, "v": 70}], "pos": -1.0, "size": 1.30000007, "_time": 4.078125}, {"$id": 11, "sounds": [{"d": 0.553977, "p": 84, "v": 100}], "pos": 2.0, "size": 1.0, "_time": 4.765625}, {"$id": 12, "sounds": [{"d": 0.46875, "p": 74, "v": 72}, {"d": 0.46875, "p": 66, "v": 68}], "pos": -2.0, "size": 1.30000007, "_time": 5.3203125}, {"$id": 13, "sounds": [{"d": 0.4616475, "p": 81, "v": 92}], "pos": 1.0, "size": 1.0, "_time": 5.328125}, {"$id": 14, "sounds": [{"d": 0.213068008, "p": 81, "v": 93}], "size": 1.0, "_time": 6.46484375, "pos": 0}, {"$id": 15, "sounds": [{"d": 0.127841, "p": 82, "v": 91}], "pos": 2.0, "size": 1.0, "_time": 6.67578125}, {"$id": 16, "sounds": [{"d": 0.340909, "p": 69, "v": 73}, {"d": 0.340909, "p": 65, "v": 67}], "pos": -1.0, "size": 1.30000007, "_time": 6.8046875}, {"$id": 17, "sounds": [{"d": 0.340909, "p": 81, "v": 89}], "pos": 1.0, "size": 1.0, "_time": 6.8046875}, {"$id": 18, "sounds": [{"d": 0.2201705, "p": 77, "v": 92}], "pos": 1.0, "size": 1.0, "_time": 7.14453125}, {"$id": 19, "sounds": [{"d": 0.127841, "p": 77, "v": 92}], "pos": 1.0, "size": 1.0, "_time": 7.36328125}, {"$id": 20, "sounds": [{"d": 0.205966, "p": 72, "v": 69}], "pos": -1.0, "size": 1.0, "_time": 7.4921875}, {"$id": 21, "sounds": [{"d": 0.340909, "p": 74, "v": 90}], "size": 1.0, "_time": 7.69921875, "pos": 0}, {"$id": 22, "sounds": [{"d": 0.134943008, "p": 79, "v": 88}], "pos": 1.0, "size": 1.0, "_time": 8.0390625}, {"$id": 23, "sounds": [{"d": 0.213068008, "p": 67, "v": 67}, {"w": 0.0078125, "d": 0.205966, "p": 57, "v": 73}], "pos": -1.0, "size": 1.30000007, "_time": 8.175781}, {"$id": 24, "sounds": [{"d": 0.46875, "p": 81, "v": 91}], "pos": 2.0, "size": 1.0, "_time": 8.386719}, {"$id": 25, "sounds": [{"d": 0.120738983, "p": 72, "v": 68}], "pos": -2.0, "size": 1.0, "_time": 9.078125}, {"$id": 26, "sounds": [{"d": 0.205966, "p": 81, "v": 88}], "size": 1.0, "_time": 9.199219, "pos": 0}, {"$id": 27, "sounds": [{"d": 0.127841, "p": 82, "v": 89}], "pos": 2.0, "size": 1.0, "_time": 9.402344}, {"$id": 28, "sounds": [{"d": 0.340909, "p": 69, "v": 72}, {"w": 0.0078125, "d": 0.333807, "p": 65, "v": 71}], "pos": -1.0, "size": 1.30000007, "_time": 9.53125}, {"$id": 29, "sounds": [{"d": 0.333807, "p": 81, "v": 87}], "pos": 1.0, "size": 1.0, "_time": 9.5390625}, {"$id": 30, "sounds": [{"d": 0.205966, "p": 77, "v": 93}], "pos": 1.0, "size": 1.0, "_time": 9.878906}, {"$id": 31, "sounds": [{"d": 0.134943008, "p": 77, "v": 89}], "pos": 1.0, "size": 1.0, "_time": 10.0859375}, {"$id": 32, "sounds": [{"d": 0.213068008, "p": 72, "v": 70}], "pos": -1.0, "size": 1.0, "_time": 10.21875}, {"$id": 33, "sounds": [{"d": 0.340909, "p": 74, "v": 87}], "size": 1.0, "_time": 10.4335938, "pos": 0}, {"$id": 34, "sounds": [{"d": 0.120738983, "p": 79, "v": 91}], "pos": 1.0, "size": 1.0, "_time": 10.7734375}, {"$id": 35, "sounds": [{"d": 0.553977, "p": 70, "v": 70}, {"d": 0.553977, "p": 60, "v": 69}], "pos": -1.0, "size": 1.30000007, "_time": 10.9023438}, {"$id": 36, "sounds": [{"d": 0.546875, "p": 84, "v": 79}], "pos": 2.0, "size": 1.0, "_time": 10.9101563}, {"$id": 37, "sounds": [{"d": 0.46875, "p": 81, "v": 91}], "pos": 1.0, "size": 1.0, "_time": 11.4570313}, {"$id": 38, "sounds": [{"d": 0.333807, "p": 77, "v": 91}], "size": 1.0, "_time": 11.9257813, "pos": 0}, {"$id": 39, "sounds": [{"d": 0.561079, "p": 65, "v": 82}, {"w": 0.0078125, "d": 0.553977, "p": 69, "v": 83}], "pos": -1.0, "size": 1.30000007, "_time": 12.2578125}, {"$id": 40, "sounds": [{"d": 0.461648, "p": 72, "v": 77}], "pos": -2.0, "size": 1.0, "_time": 12.8203125}, {"$id": 41, "sounds": [{"d": 0.561079, "p": 72, "v": 82}, {"d": 0.561079, "p": 67, "v": 80}], "pos": -1.0, "size": 1.30000007, "_time": 13.28125}, {"$id": 42, "sounds": [{"d": 0.553977, "p": 84, "v": 100}], "pos": 2.0, "size": 1.0, "_time": 13.2890625}, {"$id": 43, "sounds": [{"d": 0.120738983, "p": 67, "v": 89}], "pos": -2.0, "size": 1.0, "_time": 13.84375}, {"$id": 44, "sounds": [{"d": 0.227272987, "p": 72, "v": 87}], "pos": -1.0, "size": 1.0, "_time": 13.9648438}, {"$id": 45, "sounds": [{"d": 0.120738983, "p": 79, "v": 92}], "pos": 1.0, "size": 1.0, "_time": 14.1914063}, {"$id": 46, "sounds": [{"d": 0.340909, "p": 84, "v": 100}], "pos": 2.0, "size": 1.0, "_time": 14.3125}, {"$id": 47, "sounds": [{"d": 0.333807, "p": 82, "v": 87}], "pos": 1.0, "size": 1.0, "_time": 14.6523438}, {"$id": 48, "sounds": [{"d": 0.348011017, "p": 62, "v": 83}, {"d": 0.348011017, "p": 65, "v": 80}, {"w": 0.015625, "d": 0.333807, "p": 69, "v": 78}], "pos": -2.0, "size": 1.30000007, "_time": 14.984375}, {"$id": 49, "sounds": [{"d": 0.340909, "p": 81, "v": 89}], "size": 1.0, "_time": 14.9921875, "pos": 0}, {"$id": 50, "sounds": [{"d": 0.220170021, "p": 82, "v": 91}], "pos": 1.0, "size": 1.0, "_time": 15.3320313}, {"$id": 51, "sounds": [{"d": 0.340909958, "p": 84, "v": 100}], "pos": 2.0, "size": 1.0, "_time": 15.6679688}, {"$id": 52, "sounds": [{"d": 0.6818199, "p": 65, "v": 80}, {"d": 0.6818199, "p": 61, "v": 81}], "pos": -1.0, "size": 1.30000007, "_time": 16.0078125}, {"$id": 53, "sounds": [{"d": 0.667614, "p": 77, "v": 91}], "pos": 1.0, "size": 1.0, "_time": 16.0234375}, {"$id": 54, "sounds": [{"d": 0.348011017, "p": 72, "v": 80}], "pos": -2.0, "size": 1.0, "_time": 16.6914063}, {"$id": 55, "sounds": [{"d": 0.326704025, "p": 79, "v": 91}], "pos": 1.0, "size": 1.0, "_time": 17.046875}, {"$id": 56, "sounds": [{"d": 0.340909958, "p": 77, "v": 93}], "size": 1.0, "_time": 17.3710938, "pos": 0}, {"$id": 57, "sounds": [{"d": 0.220170975, "p": 69, "v": 77}, {"w": 0.00390625, "d": 0.213068008, "p": 65, "v": 77}], "pos": -1.0, "size": 1.30000007, "_time": 17.7148438}, {"$id": 58, "sounds": [{"d": 0.127840042, "p": 72, "v": 93}], "pos": -2.0, "size": 1.0, "_time": 17.9335938}, {"$id": 59, "sounds": [{"d": 0.213068008, "p": 77, "v": 91}], "size": 1.0, "_time": 18.0625, "pos": 0}, {"$id": 60, "sounds": [{"d": 0.127840042, "p": 79, "v": 91}], "pos": -1.0, "size": 1.0, "_time": 18.2734375}, {"$id": 61, "sounds": [{"d": 0.205965042, "p": 81, "v": 90}], "pos": 1.0, "size": 1.0, "_time": 18.4023438}, {"$id": 62, "sounds": [{"d": 0.127840042, "p": 77, "v": 89}], "size": 1.0, "_time": 18.609375, "pos": 0}, {"$id": 63, "sounds": [{"d": 0.681818, "p": 84, "v": 100}], "pos": 2.0, "size": 1.0, "_time": 18.734375}, {"$id": 64, "sounds": [{"d": 0.681818, "p": 72, "v": 79}, {"w": 0.0078125, "d": 0.674715042, "p": 67, "v": 83}], "pos": -2.0, "size": 1.30000007, "_time": 18.734375}, {"$id": 65, "sounds": [{"d": 0.333807, "p": 86, "v": 100}], "pos": 1.0, "size": 1.0, "_time": 19.4257813}, {"$id": 66, "sounds": [{"d": 0.333807, "p": 84, "v": 100}], "size": 1.0, "_time": 19.765625, "pos": 0}, {"$id": 67, "sounds": [{"d": 0.340909958, "p": 82, "v": 91}], "pos": -1.0, "size": 1.0, "_time": 20.0976563}, {"$id": 68, "sounds": [{"d": 0.340909958, "p": 65, "v": 82}, {"w": 0.0078125, "d": 0.333807, "p": 69, "v": 79}, {"w": 0.0078125, "d": 0.333807, "p": 62, "v": 83}], "pos": -2.0, "size": 1.30000007, "_time": 20.4414063}, {"$id": 69, "sounds": [{"d": 0.340909958, "p": 81, "v": 93}], "pos": 1.0, "size": 1.0, "_time": 20.4414063}, {"$id": 70, "sounds": [{"d": 0.333807, "p": 82, "v": 93}], "pos": -1.0, "size": 1.0, "_time": 20.7890625}, {"$id": 71, "sounds": [{"d": 0.333807, "p": 84, "v": 100}], "size": 1.0, "_time": 21.1289063, "pos": 0}, {"$id": 72, "sounds": [{"d": 0.205965042, "p": 89, "v": 100}], "pos": 2.0, "size": 1.0, "_time": 21.46875}, {"$id": 73, "sounds": [{"d": 0.46875, "p": 89, "v": 100}], "pos": 2.0, "size": 1.0, "_time": 21.6757813}, {"$id": 74, "sounds": [{"d": 0.454545975, "p": 69, "v": 77}, {"d": 0.454545975, "p": 65, "v": 77}], "pos": -1.0, "size": 1.30000007, "_time": 21.6914063}, {"$id": 75, "sounds": [{"d": 0.561079, "p": 61, "v": 80}, {"w": 0.015625, "d": 0.546875, "p": 65, "v": 79}], "pos": -2.0, "size": 1.30000007, "_time": 22.1445313}, {"$id": 76, "sounds": [{"d": 0.561079, "p": 72, "v": 78}], "pos": 1.0, "size": 1.0, "_time": 22.1445313}, {"$id": 77, "sounds": [{"d": 0.461647034, "p": 70, "v": 82}], "size": 1.0, "_time": 22.7070313, "pos": 0}, {"$id": 78, "sounds": [{"d": 0.674716949, "p": 69, "v": 73}], "pos": 1.0, "size": 1.0, "_time": 23.1757813}, {"$id": 79, "sounds": [{"d": 0.667614, "p": 65, "v": 71}], "pos": -1.0, "size": 1.30000007, "_time": 23.1835938}, {"$id": 80, "sounds": [{"d": 0.227272034, "p": 77, "v": 87}], "pos": 2.0, "size": 1.0, "_time": 23.8476563}, {"$id": 81, "sounds": [{"d": 0.127840042, "p": 76, "v": 88}], "pos": 1.0, "size": 1.0, "_time": 24.078125}, {"$id": 82, "sounds": [{"d": 0.213068008, "p": 72, "v": 92}], "pos": -1.0, "size": 1.0, "_time": 24.203125}, {"$id": 83, "sounds": [{"d": 0.333807, "p": 74, "v": 92}], "size": 1.0, "_time": 24.4179688, "pos": 0}, {"$id": 84, "sounds": [{"d": 0.461647034, "p": 72, "v": 92}], "pos": -1.0, "size": 1.0, "_time": 24.75}, {"$id": 85, "sounds": [{"d": 0.333807, "p": 69, "v": 87}], "pos": -2.0, "size": 1.0, "_time": 25.4335938}, {"$id": 86, "sounds": [{"d": 0.127840042, "p": 70, "v": 93}], "size": 1.0, "_time": 25.765625, "pos": 0}, {"$id": 87, "sounds": [{"d": 0.553977966, "p": 64, "v": 70}, {"d": 0.553977966, "p": 67, "v": 73}], "pos": -1.0, "size": 1.30000007, "_time": 25.8945313}, {"$id": 88, "sounds": [{"d": 0.546875, "p": 72, "v": 90}], "pos": 1.0, "size": 1.0, "_time": 25.9023438}, {"$id": 89, "sounds": [{"d": 0.134943008, "p": 69, "v": 90}], "pos": -2.0, "size": 1.0, "_time": 26.4492188}, {"$id": 90, "sounds": [{"d": 0.553977966, "p": 72, "v": 90}], "pos": -1.0, "size": 1.0, "_time": 26.5820313}, {"$id": 91, "sounds": [{"d": 0.120738983, "p": 74, "v": 93}], "pos": 2.0, "size": 1.0, "_time": 27.1367188}, {"$id": 92, "sounds": [{"d": 0.340909958, "p": 69, "v": 88}], "pos": 1.0, "size": 1.0, "_time": 27.2578125}, {"$id": 93, "sounds": [{"d": 0.220170975, "p": 67, "v": 93}], "pos": -1.0, "size": 1.0, "_time": 27.5976563}, {"$id": 94, "sounds": [{"d": 0.127840042, "p": 69, "v": 87}], "pos": 1.0, "size": 1.0, "_time": 27.8203125}, {"$id": 95, "sounds": [{"d": 0.461647034, "p": 67, "v": 69}], "pos": -1.0, "size": 1.0, "_time": 28.1601563}, {"$id": 96, "sounds": [{"d": 0.674716949, "p": 62, "v": 73}], "pos": -1.0, "size": 1.30000007, "_time": 28.6289063}, {"$id": 97, "sounds": [{"d": 0.667614, "p": 65, "v": 68}], "pos": 1.0, "size": 1.0, "_time": 28.6367188}, {"$id": 98, "sounds": [{"d": 0.220169067, "p": 77, "v": 90}], "pos": 2.0, "size": 1.0, "_time": 29.3046875}, {"$id": 99, "sounds": [{"d": 0.127840042, "p": 76, "v": 89}], "pos": 1.0, "size": 1.0, "_time": 29.5234375}, {"$id": 100, "sounds": [{"d": 0.205965042, "p": 72, "v": 92}], "pos": -1.0, "size": 1.0, "_time": 29.6523438}, {"$id": 101, "sounds": [{"d": 0.348011017, "p": 74, "v": 93}], "size": 1.0, "_time": 29.859375, "pos": 0}, {"$id": 102, "sounds": [{"d": 0.120738983, "p": 72, "v": 93}], "pos": -2.0, "size": 1.0, "_time": 30.2070313}, {"$id": 103, "sounds": [{"d": 0.348011017, "p": 72, "v": 88}], "pos": -2.0, "size": 1.0, "_time": 30.328125}, {"$id": 104, "sounds": [{"d": 0.340909958, "p": 72, "v": 91}], "pos": -2.0, "size": 1.0, "_time": 30.8945313}, {"$id": 105, "sounds": [{"d": 0.113636017, "p": 72, "v": 90}], "size": 1.0, "_time": 31.234375, "pos": 0}, {"$id": 106, "sounds": [{"d": 0.348012924, "p": 69, "v": 72}, {"w": 0.015625, "d": 0.333807, "p": 65, "v": 67}], "pos": -1.0, "size": 1.30000007, "_time": 31.3476563}, {"$id": 107, "sounds": [{"d": 0.340909958, "p": 79, "v": 92}], "pos": 1.0, "size": 1.0, "_time": 31.3554688}, {"$id": 108, "sounds": [{"d": 0.205965042, "p": 77, "v": 91}], "size": 1.0, "_time": 31.6992188, "pos": 0}, {"$id": 109, "sounds": [{"d": 0.127840042, "p": 79, "v": 92}], "pos": 1.0, "size": 1.0, "_time": 31.9023438}, {"$id": 110, "sounds": [{"d": 0.127841949, "p": 81, "v": 89}], "pos": 2.0, "size": 1.0, "_time": 32.2460938}, {"$id": 111, "sounds": [{"d": 0.340908051, "p": 79, "v": 88}], "pos": 1.0, "size": 1.0, "_time": 32.59375}, {"$id": 112, "sounds": [{"d": 0.120738983, "p": 77, "v": 91}], "size": 1.0, "_time": 32.9335938, "pos": 0}, {"$id": 113, "sounds": [{"d": 0.553977966, "p": 72, "v": 73}], "pos": 1.0, "size": 1.0, "_time": 33.0546875}, {"$id": 114, "sounds": [{"d": 0.553977966, "p": 65, "v": 72}, {"d": 0.553977966, "p": 61, "v": 71}], "pos": -1.0, "size": 1.30000007, "_time": 33.0546875}, {"$id": 115, "sounds": [{"d": 0.454544067, "p": 70, "v": 69}], "size": 1.0, "_time": 33.6210938, "pos": 0}, {"$id": 116, "sounds": [{"d": 0.6889229, "p": 69, "v": 68}], "pos": 1.0, "size": 1.0, "_time": 34.078125}, {"$id": 117, "sounds": [{"d": 0.674716949, "p": 65, "v": 69}], "pos": -1.0, "size": 1.30000007, "_time": 34.0898438}, {"$id": 118, "sounds": [{"d": 0.220169067, "p": 77, "v": 89}], "pos": 2.0, "size": 1.0, "_time": 34.765625}, {"$id": 119, "sounds": [{"d": 0.326705933, "p": 76, "v": 93}], "pos": 1.0, "size": 1.0, "_time": 34.984375}, {"$id": 120, "sounds": [{"d": 0.340908051, "p": 74, "v": 91}], "size": 1.0, "_time": 35.3125, "pos": 0}, {"$id": 121, "sounds": [{"d": 0.134944916, "p": 72, "v": 87}], "pos": -1.0, "size": 1.0, "_time": 35.6523438}, {"$id": 122, "sounds": [{"d": 0.340908051, "p": 69, "v": 90}], "pos": -2.0, "size": 1.0, "_time": 36.3476563}, {"$id": 123, "sounds": [{"d": 0.113636017, "p": 70, "v": 89}], "size": 1.0, "_time": 36.6914063, "pos": 0}, {"$id": 124, "sounds": [{"d": 0.561080933, "p": 64, "v": 73}, {"d": 0.561080933, "p": 67, "v": 69}], "pos": -1.0, "size": 1.30000007, "_time": 36.8046875}, {"$id": 125, "sounds": [{"d": 0.553977966, "p": 72, "v": 92}], "pos": 1.0, "size": 1.0, "_time": 36.8125}, {"$id": 126, "sounds": [{"d": 0.134944916, "p": 69, "v": 92}], "pos": -2.0, "size": 1.0, "_time": 37.36328}, {"$id": 127, "sounds": [{"d": 0.546875, "p": 72, "v": 89}], "pos": -1.0, "size": 1.0, "_time": 37.5}, {"$id": 128, "sounds": [{"d": 0.127841949, "p": 74, "v": 91}], "pos": 2.0, "size": 1.0, "_time": 38.046875}, {"$id": 129, "sounds": [{"d": 0.220169067, "p": 69, "v": 93}], "pos": 1.0, "size": 1.0, "_time": 38.17578}, {"$id": 130, "sounds": [{"d": 0.340908051, "p": 67, "v": 91}], "pos": -1.0, "size": 1.0, "_time": 38.39453}, {"$id": 131, "sounds": [{"d": 0.120738983, "p": 69, "v": 90}], "pos": 1.0, "size": 1.0, "_time": 38.734375}, {"$id": 132, "sounds": [{"d": 0.461647034, "p": 67, "v": 68}], "pos": -1.0, "size": 1.0, "_time": 39.0703125}, {"$id": 133, "sounds": [{"d": 0.688919067, "p": 65, "v": 72}], "pos": 1.0, "size": 1.0, "_time": 39.53125}, {"$id": 134, "sounds": [{"d": 0.688919067, "p": 62, "v": 70}], "pos": -1.0, "size": 1.30000007, "_time": 39.53125}, {"$id": 135, "sounds": [{"d": 0.205966949, "p": 77, "v": 87}], "pos": 2.0, "size": 1.0, "_time": 40.21875}, {"$id": 136, "sounds": [{"d": 0.355113983, "p": 76, "v": 91}], "pos": 1.0, "size": 1.0, "_time": 40.42578}, {"$id": 137, "sounds": [{"d": 0.113636017, "p": 74, "v": 89}], "size": 1.0, "_time": 40.78125, "pos": 0}, {"$id": 138, "sounds": [{"d": 0.134944916, "p": 72, "v": 90}], "pos": 1.0, "size": 1.0, "_time": 41.109375}, {"$id": 139, "sounds": [{"d": 0.220169067, "p": 74, "v": 92}], "pos": 2.0, "size": 1.0, "_time": 41.2421875}, {"$id": 140, "sounds": [{"d": 0.127841949, "p": 72, "v": 92}], "pos": 1.0, "size": 1.0, "_time": 41.4648438}, {"$id": 141, "sounds": [{"d": 0.205966949, "p": 67, "v": 72}], "pos": -1.0, "size": 1.0, "_time": 41.5898438}, {"$id": 142, "sounds": [{"d": 0.127841949, "p": 72, "v": 91}], "pos": 1.0, "size": 1.0, "_time": 41.796875}, {"$id": 143, "sounds": [{"d": 0.205966949, "p": 69, "v": 71}], "size": 1.0, "_time": 41.92578, "pos": 0}, {"$id": 144, "sounds": [{"d": 0.127841949, "p": 72, "v": 90}], "pos": 1.0, "size": 1.0, "_time": 42.1289063}, {"$id": 145, "sounds": [{"d": 0.348011017, "p": 65, "v": 69}, {"w": 0.0078125, "d": 0.340908051, "p": 67, "v": 67}], "pos": -1.0, "size": 1.30000007, "_time": 42.2578125}, {"$id": 146, "sounds": [{"d": 0.340908051, "p": 79, "v": 92}], "pos": 2.0, "size": 1.0, "_time": 42.265625}, {"$id": 147, "sounds": [{"d": 0.220169067, "p": 77, "v": 92}], "size": 1.0, "_time": 42.60547, "pos": 0}, {"$id": 148, "sounds": [{"d": 0.120738983, "p": 79, "v": 90}], "pos": 1.0, "size": 1.0, "_time": 42.828125}, {"$id": 149, "sounds": [{"d": 0.340908051, "p": 81, "v": 91}], "pos": 2.0, "size": 1.0, "_time": 43.16797}, {"$id": 150, "sounds": [{"d": 0.340908051, "p": 79, "v": 91}], "pos": 1.0, "size": 1.0, "_time": 43.5078125}, {"$id": 151, "sounds": [{"d": 0.454544067, "p": 77, "v": 87}], "size": 1.0, "_time": 43.8476563, "pos": 0}, {"$id": 152, "sounds": [{"d": 0.348011017, "p": 51, "v": 72}], "pos": -2.0, "size": 1.30000007, "_time": 44.3046875}, {"$id": 153, "sounds": [{"d": 0.326705933, "p": 77, "v": 93}], "pos": 1.0, "size": 1.0, "_time": 44.6601563}, {"$id": 154, "sounds": [{"d": 0.561080933, "p": 65, "v": 73}, {"w": 0.015625, "d": 0.546875, "p": 72, "v": 67}], "pos": -2.0, "size": 1.30000007, "_time": 44.984375}, {"$id": 155, "sounds": [{"d": 0.553977966, "p": 84, "v": 100}], "pos": 2.0, "size": 1.0, "_time": 44.9921875}, {"$id": 156, "sounds": [{"d": 0.127841949, "p": 81, "v": 91}], "pos": -1.0, "size": 1.0, "_time": 45.546875}, {"$id": 157, "sounds": [{"d": 0.539772034, "p": 81, "v": 89}], "pos": -1.0, "size": 1.0, "_time": 45.6835938}, {"$id": 158, "sounds": [{"d": 0.127841949, "p": 82, "v": 90}], "pos": 1.0, "size": 1.0, "_time": 46.2226563}, {"$id": 159, "sounds": [{"d": 0.326705933, "p": 81, "v": 91}], "pos": -1.0, "size": 1.0, "_time": 46.36328}, {"$id": 160, "sounds": [{"d": 0.220169067, "p": 77, "v": 87}], "pos": -2.0, "size": 1.0, "_time": 46.6914063}, {"$id": 161, "sounds": [{"d": 0.127841949, "p": 79, "v": 87}], "size": 1.0, "_time": 46.9101563, "pos": 0}, {"$id": 162, "sounds": [{"d": 0.127841949, "p": 77, "v": 88}], "pos": -1.0, "size": 1.0, "_time": 47.25}, {"$id": 163, "sounds": [{"d": 0.220169067, "p": 79, "v": 91}], "size": 1.0, "_time": 47.3789063, "pos": 0}, {"$id": 164, "sounds": [{"d": 0.113636017, "p": 77, "v": 92}], "pos": -1.0, "size": 1.0, "_time": 47.5976563}, {"$id": 165, "sounds": [{"d": 0.340908051, "p": 72, "v": 67}, {"w": 0.00390625, "d": 0.333805084, "p": 67, "v": 73}], "pos": -2.0, "size": 1.30000007, "_time": 47.7148438}, {"$id": 166, "sounds": [{"d": 0.340908051, "p": 79, "v": 92}], "size": 1.0, "_time": 47.7148438, "pos": 0}, {"$id": 167, "sounds": [{"d": 0.213069916, "p": 77, "v": 87}], "pos": -1.0, "size": 1.0, "_time": 48.0546875}, {"$id": 168, "sounds": [{"d": 0.134944916, "p": 79, "v": 89}], "size": 1.0, "_time": 48.265625, "pos": 0}, {"$id": 169, "sounds": [{"d": 0.348011017, "p": 81, "v": 87}], "pos": 1.0, "size": 1.0, "_time": 48.61328}, {"$id": 170, "sounds": [{"d": 0.461647034, "p": 77, "v": 88}], "pos": -1.0, "size": 1.0, "_time": 48.9648438}, {"$id": 171, "sounds": [{"d": 0.213069916, "p": 72, "v": 71}], "pos": -2.0, "size": 1.0, "_time": 49.42578}, {"$id": 172, "sounds": [{"d": 0.120738983, "p": 74, "v": 57}], "pos": -1.0, "size": 1.0, "_time": 49.63672}, {"$id": 173, "sounds": [{"d": 0.3338089, "p": 77, "v": 63}], "pos": 1.0, "size": 1.0, "_time": 49.765625}, {"$id": 174, "sounds": [{"d": 0.220169067, "p": 74, "v": 89}], "pos": -1.0, "size": 1.0, "_time": 50.0976563}, {"$id": 175, "sounds": [{"d": 0.120738983, "p": 74, "v": 92}], "pos": -1.0, "size": 1.0, "_time": 50.3203125}, {"$id": 176, "sounds": [{"d": 0.348011017, "p": 65, "v": 68}, {"w": 0.0078125, "d": 0.340908051, "p": 72, "v": 68}], "pos": -2.0, "size": 1.30000007, "_time": 50.4414063}, {"$id": 177, "sounds": [{"d": 0.348011017, "p": 79, "v": 87}], "pos": 2.0, "size": 1.0, "_time": 50.4414063}, {"$id": 178, "sounds": [{"d": 0.213069916, "p": 77, "v": 89}], "pos": 1.0, "size": 1.0, "_time": 50.7890625}, {"$id": 179, "sounds": [{"d": 0.340908051, "p": 77, "v": 90}], "pos": 1.0, "size": 1.0, "_time": 51.0}, {"$id": 180, "sounds": [{"d": 0.120738983, "p": 74, "v": 89}], "pos": -1.0, "size": 1.0, "_time": 51.34375}, {"$id": 181, "sounds": [{"d": 0.688919067, "p": 77, "v": 93}], "pos": 1.0, "size": 1.0, "_time": 51.4648438}, {"$id": 182, "sounds": [{"d": 0.333805084, "p": 81, "v": 61}], "size": 0.6999999, "_time": 52.1523438, "pos": 0}, {"$id": 183, "sounds": [{"d": 0.134944916, "p": 82, "v": 60}], "pos": 1.0, "size": 0.6999999, "_time": 52.69922}, {"$id": 184, "sounds": [{"d": 0.220169067, "p": 74, "v": 91}], "pos": -1.0, "size": 1.0, "_time": 52.83203}, {"$id": 185, "sounds": [{"d": 0.113636017, "p": 74, "v": 88}], "pos": -1.0, "size": 1.0, "_time": 53.0546875}, {"$id": 186, "sounds": [{"d": 0.340908051, "p": 72, "v": 68}, {"d": 0.340908051, "p": 65, "v": 67}, {"w": 0.0078125, "d": 0.333805084, "p": 68, "v": 69}, {"w": 0.0078125, "d": 0.333805084, "p": 69, "v": 73}], "pos": -2.0, "size": 1.30000007, "_time": 53.16797}, {"$id": 187, "sounds": [{"d": 0.333805084, "p": 79, "v": 92}], "pos": 2.0, "size": 1.0, "_time": 53.17578}, {"$id": 188, "sounds": [{"d": 0.220169067, "p": 77, "v": 88}], "pos": 1.0, "size": 1.0, "_time": 53.5078125}, {"$id": 189, "sounds": [{"d": 0.113636017, "p": 77, "v": 91}], "pos": 1.0, "size": 1.0, "_time": 53.734375}, {"$id": 190, "sounds": [{"d": 0.127841949, "p": 74, "v": 90}], "pos": -1.0, "size": 1.0, "_time": 54.0703125}, {"$id": 191, "sounds": [{"d": 0.205966949, "p": 77, "v": 90}], "pos": 1.0, "size": 1.0, "_time": 54.19922}, {"$id": 192, "sounds": [{"d": 0.482955933, "p": 63, "v": 71}, {"d": 0.482955933, "p": 72, "v": 70}], "pos": -2.0, "size": 1.30000007, "_time": 54.4023438}, {"$id": 193, "sounds": [{"d": 0.333805084, "p": 79, "v": 60}], "pos": 2.0, "size": 1.0, "_time": 54.88672}, {"$id": 194, "sounds": [{"d": 0.127841949, "p": 74, "v": 62}], "pos": -1.0, "size": 1.0, "_time": 55.4335938}, {"$id": 195, "sounds": [{"d": 0.333805084, "p": 77, "v": 87}], "pos": 1.0, "size": 1.0, "_time": 55.5625}, {"$id": 196, "sounds": [{"d": 0.553977966, "p": 72, "v": 71}, {"w": 0.015625, "d": 0.539772034, "p": 65, "v": 73}], "pos": -2.0, "size": 1.30000007, "_time": 55.89453}, {"$id": 197, "sounds": [{"d": 0.546875, "p": 84, "v": 100}], "pos": 2.0, "size": 1.0, "_time": 55.9023438}, {"$id": 198, "sounds": [{"d": 0.127841949, "p": 82, "v": 100}], "pos": 1.0, "size": 1.0, "_time": 56.44922}, {"$id": 199, "sounds": [{"d": 0.561080933, "p": 81, "v": 91}], "size": 1.0, "_time": 56.578125, "pos": 0}, {"$id": 200, "sounds": [{"d": 0.120738983, "p": 82, "v": 100}], "pos": 1.0, "size": 1.0, "_time": 57.13672}, {"$id": 201, "sounds": [{"d": 0.340908051, "p": 81, "v": 90}], "size": 1.0, "_time": 57.265625, "pos": 0}, {"$id": 202, "sounds": [{"d": 0.205966949, "p": 77, "v": 93}], "pos": -1.0, "size": 1.0, "_time": 57.60547}, {"$id": 203, "sounds": [{"d": 0.142047882, "p": 77, "v": 91}], "pos": -1.0, "size": 1.0, "_time": 57.8125}, {"$id": 204, "sounds": [{"d": 0.120738983, "p": 70, "v": 72}], "pos": -2.0, "size": 1.0, "_time": 58.1601563}, {"$id": 205, "sounds": [{"d": 0.220169067, "p": 77, "v": 91}], "size": 1.0, "_time": 58.28125, "pos": 0}, {"$id": 206, "sounds": [{"d": 0.120738983, "p": 77, "v": 88}], "pos": -1.0, "size": 1.0, "_time": 58.5}, {"$id": 207, "sounds": [{"d": 0.340908051, "p": 72, "v": 72}, {"d": 0.340908051, "p": 67, "v": 68}], "pos": -2.0, "size": 1.30000007, "_time": 58.6289063}, {"$id": 208, "sounds": [{"d": 0.340908051, "p": 79, "v": 92}], "pos": 1.0, "size": 1.0, "_time": 58.6289063}, {"$id": 209, "sounds": [{"d": 0.220169067, "p": 77, "v": 93}], "pos": -1.0, "size": 1.0, "_time": 58.96875}, {"$id": 210, "sounds": [{"d": 0.333805084, "p": 79, "v": 88}], "pos": 1.0, "size": 1.0, "_time": 59.1914063}, {"$id": 211, "sounds": [{"d": 0.348011017, "p": 84, "v": 100}], "pos": 2.0, "size": 1.0, "_time": 59.5234375}, {"$id": 212, "sounds": [{"d": 0.454544067, "p": 77, "v": 90}], "pos": 1.0, "size": 1.0, "_time": 59.8710938}, {"$id": 213, "sounds": [{"d": 0.348011017, "p": 79, "v": 58}], "size": 1.0, "_time": 60.328125, "pos": 0}, {"$id": 214, "sounds": [{"d": 0.127841949, "p": 77, "v": 58}], "pos": 1.0, "size": 1.0, "_time": 60.88672}, {"$id": 215, "sounds": [{"d": 0.220169067, "p": 74, "v": 89}], "pos": -1.0, "size": 1.0, "_time": 61.015625}, {"$id": 216, "sounds": [{"d": 0.113636017, "p": 76, "v": 93}], "size": 1.0, "_time": 61.234375, "pos": 0}, {"$id": 217, "sounds": [{"d": 0.227275848, "p": 72, "v": 69}, {"w": 0.015625, "d": 0.213069916, "p": 65, "v": 68}], "pos": -1.0, "size": 1.30000007, "_time": 61.3476563}, {"$id": 218, "sounds": [{"d": 0.220172882, "p": 77, "v": 89}], "pos": 1.0, "size": 1.0, "_time": 61.35547}, {"$id": 219, "sounds": [{"d": 0.333805084, "p": 74, "v": 89}], "size": 1.0, "_time": 61.578125, "pos": 0}, {"$id": 220, "sounds": [{"d": 0.461647034, "p": 77, "v": 87}], "pos": 1.0, "size": 1.0, "_time": 61.91797}, {"$id": 221, "sounds": [{"d": 0.333805084, "p": 74, "v": 90}], "size": 1.0, "_time": 62.3789063, "pos": 0}, {"$id": 222, "sounds": [{"d": 0.340908051, "p": 77, "v": 92}], "pos": 1.0, "size": 1.0, "_time": 62.7148438}, {"$id": 223, "sounds": [{"d": 0.340908051, "p": 74, "v": 87}], "size": 1.0, "_time": 63.0546875, "pos": 0}, {"$id": 224, "sounds": [{"d": 0.340908051, "p": 77, "v": 92}], "pos": 1.0, "size": 1.0, "_time": 63.39453}, {"$id": 225, "sounds": [{"d": 0.348014832, "p": 84, "v": 100}], "pos": 2.0, "size": 1.0, "_time": 63.734375}, {"$id": 226, "sounds": [{"d": 0.3338089, "p": 48, "v": 80}], "pos": -1.0, "size": 1.2, "_time": 64.08203}, {"$id": 227, "sounds": [{"d": 0.3338089, "p": 62, "v": 82}], "pos": 1.0, "size": 1.2, "_time": 64.08203}, {"$id": 228, "sounds": [{"d": 0.348014832, "p": 48, "v": 77}], "pos": -1.0, "size": 1.4000001, "_time": 64.41797}, {"$id": 229, "sounds": [{"d": 0.340911865, "p": 58, "v": 83}], "pos": 1.0, "size": 1.4000001, "_time": 64.42578}, {"$id": 230, "sounds": [{"d": 0.3338089, "p": 58, "v": 77}, {"w": 0.0078125, "d": 0.326705933, "p": 62, "v": 79}], "pos": 1.0, "size": 1.60000014, "_time": 64.765625}, {"$id": 231, "sounds": [{"d": 0.326705933, "p": 48, "v": 77}], "pos": -1.0, "size": 1.60000014, "_time": 64.77344}, {"$id": 232, "sounds": [{"d": 0.348014832, "p": 65, "v": 81}, {"w": 0.0078125, "d": 0.340911865, "p": 62, "v": 82}, {"w": 0.015625, "d": 0.3338089, "p": 58, "v": 82}], "pos": 1.0, "size": 1.80000019, "_time": 65.09766}, {"$id": 233, "sounds": [{"d": 0.348014832, "p": 48, "v": 77}], "pos": -1.0, "size": 1.80000019, "_time": 65.09766}, {"$id": 234, "sounds": [{"d": 1.022728, "p": 58, "v": 77}, {"d": 1.022728, "p": 62, "v": 79}, {"w": 0.00390625, "d": 1.015625, "p": 67, "v": 77}], "pos": 1.0, "size": 2.0, "_time": 65.44922}, {"$id": 235, "sounds": [{"d": 1.022728, "p": 48, "v": 77}], "pos": -1.0, "size": 2.0, "_time": 65.44922}, {"$id": 236, "sounds": [{"d": 0.3338089, "p": 72, "v": 92}], "pos": -1.0, "size": 1.0, "_time": 66.46875}, {"$id": 237, "sounds": [{"d": 0.688919067, "p": 65, "v": 80}, {"d": 0.688919067, "p": 67, "v": 78}], "pos": -2.0, "size": 1.30000007, "_time": 66.80469}, {"$id": 238, "sounds": [{"d": 0.674713135, "p": 79, "v": 100}], "size": 1.0, "_time": 66.81641, "pos": 0}, {"$id": 239, "sounds": [{"d": 0.553977966, "p": 79, "v": 100}], "size": 1.0, "_time": 67.49219, "pos": 0}, {"$id": 240, "sounds": [{"d": 0.46875, "p": 81, "v": 100}], "pos": 1.0, "size": 1.0, "_time": 68.046875}, {"$id": 241, "sounds": [{"d": 0.348014832, "p": 53, "v": 69}], "pos": -2.0, "size": 1.0, "_time": 68.515625}, {"$id": 242, "sounds": [{"d": 0.326705933, "p": 69, "v": 77}], "pos": -1.0, "size": 1.0, "_time": 68.86328}, {"$id": 243, "sounds": [{"d": 0.340911865, "p": 72, "v": 88}], "size": 1.0, "_time": 69.19141, "pos": 0}, {"$id": 244, "sounds": [{"d": 0.6818161, "p": 63, "v": 83}, {"w": 0.0078125, "d": 0.674713135, "p": 67, "v": 80}], "pos": -2.0, "size": 1.30000007, "_time": 69.53125}, {"$id": 245, "sounds": [{"d": 0.674713135, "p": 79, "v": 100}], "pos": 1.0, "size": 1.0, "_time": 69.53906}, {"$id": 246, "sounds": [{"d": 0.553977966, "p": 79, "v": 100}], "size": 1.0, "_time": 70.21875, "pos": 0}, {"$id": 247, "sounds": [{"d": 0.461647034, "p": 81, "v": 100}], "pos": 1.0, "size": 1.0, "_time": 70.77344}, {"$id": 248, "sounds": [{"d": 0.340911865, "p": 63, "v": 77}], "pos": -1.0, "size": 1.0, "_time": 71.24219}, {"$id": 249, "sounds": [{"d": 0.348014832, "p": 72, "v": 77}], "size": 1.0, "_time": 71.58203, "pos": 0}, {"$id": 250, "sounds": [{"d": 0.2130661, "p": 81, "v": 90}], "pos": 1.0, "size": 1.0, "_time": 71.93359}, {"$id": 251, "sounds": [{"d": 0.113639832, "p": 82, "v": 91}], "pos": 2.0, "size": 1.0, "_time": 72.14453}, {"$id": 252, "sounds": [{"d": 0.3551178, "p": 69, "v": 81}, {"w": 0.015625, "d": 0.340911865, "p": 65, "v": 82}], "pos": -1.0, "size": 1.30000007, "_time": 72.25781}, {"$id": 253, "sounds": [{"d": 0.348014832, "p": 81, "v": 88}], "pos": 1.0, "size": 1.0, "_time": 72.265625}, {"$id": 254, "sounds": [{"d": 0.2130661, "p": 77, "v": 90}], "pos": 1.0, "size": 1.0, "_time": 72.61328}, {"$id": 255, "sounds": [{"d": 0.127838135, "p": 77, "v": 89}], "pos": 1.0, "size": 1.0, "_time": 72.828125}, {"$id": 256, "sounds": [{"d": 0.326705933, "p": 65, "v": 81}], "pos": -1.0, "size": 1.0, "_time": 72.953125}, {"$id": 257, "sounds": [{"d": 0.220169067, "p": 77, "v": 88}], "pos": 1.0, "size": 1.0, "_time": 73.28125}, {"$id": 258, "sounds": [{"d": 0.120735168, "p": 74, "v": 87}], "size": 1.0, "_time": 73.5, "pos": 0}, {"$id": 259, "sounds": [{"d": 0.220169067, "p": 67, "v": 82}, {"w": 0.0078125, "d": 0.2130661, "p": 72, "v": 82}], "pos": -1.0, "size": 1.30000007, "_time": 73.62109}, {"$id": 260, "sounds": [{"d": 0.2130661, "p": 79, "v": 87}], "pos": 1.0, "size": 1.0, "_time": 73.62891}, {"$id": 261, "sounds": [{"d": 0.461647034, "p": 81, "v": 87}], "pos": 2.0, "size": 1.0, "_time": 73.84375}, {"$id": 262, "sounds": [{"d": 0.127838135, "p": 72, "v": 93}], "pos": -2.0, "size": 1.0, "_time": 74.515625}, {"$id": 263, "sounds": [{"d": 0.227272034, "p": 81, "v": 91}], "size": 1.0, "_time": 74.64453, "pos": 0}, {"$id": 264, "sounds": [{"d": 0.113639832, "p": 82, "v": 88}], "pos": 2.0, "size": 1.0, "_time": 74.87109}, {"$id": 265, "sounds": [{"d": 0.348014832, "p": 65, "v": 81}], "pos": -1.0, "size": 1.30000007, "_time": 74.984375}, {"$id": 266, "sounds": [{"d": 0.340911865, "p": 81, "v": 88}], "pos": 1.0, "size": 1.0, "_time": 74.99219}, {"$id": 267, "sounds": [{"d": 0.220169067, "p": 77, "v": 91}], "pos": 1.0, "size": 1.0, "_time": 75.33203}, {"$id": 268, "sounds": [{"d": 0.127838135, "p": 77, "v": 92}], "pos": 1.0, "size": 1.0, "_time": 75.55469}, {"$id": 269, "sounds": [{"d": 0.2130661, "p": 69, "v": 78}], "pos": -1.0, "size": 1.0, "_time": 75.68359}, {"$id": 270, "sounds": [{"d": 0.120735168, "p": 74, "v": 91}], "size": 1.0, "_time": 75.89453, "pos": 0}, {"$id": 271, "sounds": [{"d": 0.2130661, "p": 74, "v": 92}], "size": 1.0, "_time": 76.015625, "pos": 0}, {"$id": 272, "sounds": [{"d": 0.127838135, "p": 74, "v": 89}], "size": 1.0, "_time": 76.23047, "pos": 0}, {"$id": 273, "sounds": [{"d": 0.220169067, "p": 67, "v": 78}], "pos": -1.0, "size": 1.30000007, "_time": 76.35547}, {"$id": 274, "sounds": [{"d": 0.113639832, "p": 72, "v": 92}], "size": 1.0, "_time": 76.578125, "pos": 0}, {"$id": 275, "sounds": [{"d": 0.5681839, "p": 70, "v": 81}], "pos": -2.0, "size": 1.0, "_time": 76.69141}, {"$id": 276, "sounds": [{"d": 0.3338089, "p": 72, "v": 91}], "pos": -1.0, "size": 1.0, "_time": 77.37891}, {"$id": 277, "sounds": [{"d": 0.6818161, "p": 79, "v": 100}], "size": 1.0, "_time": 77.71484, "pos": 0}, {"$id": 278, "sounds": [{"d": 0.6818161, "p": 72, "v": 78}, {"d": 0.6818161, "p": 67, "v": 83}, {"d": 0.6818161, "p": 65, "v": 78}], "pos": -2.0, "size": 1.30000007, "_time": 77.71484}, {"$id": 279, "sounds": [{"d": 0.561080933, "p": 79, "v": 100}], "size": 1.0, "_time": 78.40234, "pos": 0}, {"$id": 280, "sounds": [{"d": 0.461647034, "p": 81, "v": 100}], "pos": 1.0, "size": 1.0, "_time": 78.96484}, {"$id": 281, "sounds": [{"d": 0.340911865, "p": 53, "v": 73}], "pos": -2.0, "size": 1.0, "_time": 79.42578}, {"$id": 282, "sounds": [{"d": 0.3338089, "p": 69, "v": 78}], "pos": -1.0, "size": 1.0, "_time": 79.765625}, {"$id": 283, "sounds": [{"d": 0.340911865, "p": 72, "v": 92}], "size": 1.0, "_time": 80.09766, "pos": 0}, {"$id": 284, "sounds": [{"d": 0.6818161, "p": 67, "v": 82}, {"d": 0.6818161, "p": 75, "v": 83}, {"w": 0.0078125, "d": 0.674713135, "p": 72, "v": 78}], "pos": -1.0, "size": 1.30000007, "_time": 80.44141}, {"$id": 285, "sounds": [{"d": 0.674713135, "p": 79, "v": 100}], "pos": 1.0, "size": 1.0, "_time": 80.44922}, {"$id": 286, "sounds": [{"d": 0.553977966, "p": 84, "v": 100}], "pos": 2.0, "size": 1.0, "_time": 81.12891}, {"$id": 287, "sounds": [{"d": 0.46875, "p": 74, "v": 80}, {"d": 0.46875, "p": 66, "v": 78}], "pos": -2.0, "size": 1.30000007, "_time": 81.68359}, {"$id": 288, "sounds": [{"d": 0.46875, "p": 81, "v": 100}], "pos": 1.0, "size": 1.0, "_time": 81.68359}, {"$id": 289, "sounds": [{"d": 0.340911865, "p": 72, "v": 81}, {"d": 0.340911865, "p": 69, "v": 78}], "pos": -1.0, "size": 1.30000007, "_time": 82.49219}, {"$id": 290, "sounds": [{"d": 0.2130661, "p": 81, "v": 91}], "size": 1.0, "_time": 82.83203, "pos": 0}, {"$id": 291, "sounds": [{"d": 0.120735168, "p": 82, "v": 91}], "pos": 2.0, "size": 1.0, "_time": 83.046875}, {"$id": 292, "sounds": [{"d": 0.348014832, "p": 69, "v": 77}, {"w": 0.0078125, "d": 0.340911865, "p": 65, "v": 77}], "pos": -1.0, "size": 1.30000007, "_time": 83.16797}, {"$id": 293, "sounds": [{"d": 0.340911865, "p": 81, "v": 93}], "pos": 1.0, "size": 1.0, "_time": 83.17578}, {"$id": 294, "sounds": [{"d": 0.2130661, "p": 77, "v": 87}], "pos": 1.0, "size": 1.0, "_time": 83.515625}, {"$id": 295, "sounds": [{"d": 0.127838135, "p": 77, "v": 87}], "pos": 1.0, "size": 1.0, "_time": 83.73047}, {"$id": 296, "sounds": [{"d": 0.205963135, "p": 72, "v": 77}], "pos": -1.0, "size": 1.0, "_time": 83.85547}, {"$id": 297, "sounds": [{"d": 0.348014832, "p": 74, "v": 90}], "size": 1.0, "_time": 84.0625, "pos": 0}, {"$id": 298, "sounds": [{"d": 0.120735168, "p": 79, "v": 89}], "pos": 1.0, "size": 1.0, "_time": 84.41016}, {"$id": 299, "sounds": [{"d": 0.220169067, "p": 67, "v": 79}, {"w": 0.015625, "d": 0.205963135, "p": 57, "v": 68}], "pos": -1.0, "size": 1.30000007, "_time": 84.53125}, {"$id": 300, "sounds": [{"d": 0.461647034, "p": 81, "v": 88}], "pos": 2.0, "size": 1.0, "_time": 84.75}, {"$id": 301, "sounds": [{"d": 0.127838135, "p": 72, "v": 89}], "pos": -1.0, "size": 1.0, "_time": 85.42578}, {"$id": 302, "sounds": [{"d": 0.198860168, "p": 81, "v": 87}], "pos": 1.0, "size": 1.0, "_time": 85.56641}, {"$id": 303, "sounds": [{"d": 0.127838135, "p": 82, "v": 90}], "pos": 2.0, "size": 1.0, "_time": 85.765625}, {"$id": 304, "sounds": [{"d": 0.340911865, "p": 81, "v": 93}], "pos": 1.0, "size": 1.0, "_time": 85.90234}, {"$id": 305, "sounds": [{"d": 0.340911865, "p": 69, "v": 79}], "pos": -1.0, "size": 1.30000007, "_time": 85.90234}, {"$id": 306, "sounds": [{"d": 0.220169067, "p": 77, "v": 91}], "pos": 1.0, "size": 1.0, "_time": 86.24219}, {"$id": 307, "sounds": [{"d": 0.113639832, "p": 77, "v": 88}], "pos": 1.0, "size": 1.0, "_time": 86.46484}, {"$id": 308, "sounds": [{"d": 0.227272034, "p": 72, "v": 83}], "pos": -1.0, "size": 1.0, "_time": 86.578125}, {"$id": 309, "sounds": [{"d": 0.340911865, "p": 74, "v": 89}], "size": 1.0, "_time": 86.80469, "pos": 0}, {"$id": 310, "sounds": [{"d": 0.113639832, "p": 79, "v": 92}], "pos": 1.0, "size": 1.0, "_time": 87.14453}, {"$id": 311, "sounds": [{"d": 0.5681839, "p": 67, "v": 77}], "pos": -1.0, "size": 1.30000007, "_time": 87.25781}, {"$id": 312, "sounds": [{"d": 0.113639832, "p": 81, "v": 88}], "pos": 2.0, "size": 1.0, "_time": 87.828125}, {"$id": 313, "sounds": [{"d": 0.348014832, "p": 69, "v": 79}], "pos": -1.0, "size": 1.30000007, "_time": 87.94141}, {"$id": 314, "sounds": [{"d": 0.326705933, "p": 77, "v": 88}], "pos": 1.0, "size": 1.0, "_time": 88.296875}, {"$id": 315, "sounds": [{"d": 0.553977966, "p": 63, "v": 67}, {"d": 0.553977966, "p": 70, "v": 81}], "pos": -1.0, "size": 1.30000007, "_time": 88.62109}, {"$id": 316, "sounds": [{"d": 0.475852966, "p": 72, "v": 83}], "pos": -1.0, "size": 1.0, "_time": 89.17578}, {"$id": 317, "sounds": [{"d": 0.2130661, "p": 74, "v": 89}], "size": 1.0, "_time": 89.65234, "pos": 0}, {"$id": 318, "sounds": [{"d": 0.127838135, "p": 74, "v": 88}], "size": 1.0, "_time": 89.86328, "pos": 0}, {"$id": 319, "sounds": [{"d": 0.220169067, "p": 80, "v": 87}], "pos": 2.0, "size": 1.0, "_time": 89.99219}, {"$id": 320, "sounds": [{"d": 0.113639832, "p": 79, "v": 91}], "pos": 1.0, "size": 1.0, "_time": 90.21484}, {"$id": 321, "sounds": [{"d": 0.227272034, "p": 63, "v": 71}, {"w": 0.00390625, "d": 0.220169067, "p": 51, "v": 73}], "pos": -2.0, "size": 1.30000007, "_time": 90.328125}, {"$id": 322, "sounds": [{"d": 0.340911865, "p": 77, "v": 92}], "size": 1.0, "_time": 90.55469, "pos": 0}, {"$id": 323, "sounds": [{"d": 0.120735168, "p": 74, "v": 89}], "pos": -1.0, "size": 1.0, "_time": 90.89453}, {"$id": 324, "sounds": [{"d": 0.3338089, "p": 77, "v": 93}], "pos": 1.0, "size": 1.0, "_time": 91.015625}, {"$id": 325, "sounds": [{"d": 0.561080933, "p": 70, "v": 81}], "size": 1.0, "_time": 91.34766, "pos": 0}, {"$id": 326, "sounds": [{"d": 0.553977966, "p": 62, "v": 71}, {"d": 0.553977966, "p": 65, "v": 82}], "pos": -2.0, "size": 1.30000007, "_time": 91.35547}, {"$id": 327, "sounds": [{"d": 0.475852966, "p": 72, "v": 81}], "pos": -1.0, "size": 1.0, "_time": 91.91016}, {"$id": 328, "sounds": [{"d": 0.205963135, "p": 74, "v": 89}], "size": 1.0, "_time": 92.38672, "pos": 0}, {"$id": 329, "sounds": [{"d": 0.120735168, "p": 74, "v": 90}], "size": 1.0, "_time": 92.59375, "pos": 0}, {"$id": 330, "sounds": [{"d": 0.220169067, "p": 80, "v": 87}], "pos": 2.0, "size": 1.0, "_time": 92.71484}, {"$id": 331, "sounds": [{"d": 0.127838135, "p": 79, "v": 91}], "pos": 1.0, "size": 1.0, "_time": 92.93359}, {"$id": 332, "sounds": [{"d": 0.2130661, "p": 50, "v": 67}, {"d": 0.2130661, "p": 62, "v": 67}], "pos": -2.0, "size": 1.30000007, "_time": 93.0625}, {"$id": 333, "sounds": [{"d": 0.348014832, "p": 77, "v": 88}], "size": 1.0, "_time": 93.27344, "pos": 0}, {"$id": 334, "sounds": [{"d": 0.113639832, "p": 74, "v": 92}], "pos": -1.0, "size": 1.0, "_time": 93.62109}, {"$id": 335, "sounds": [{"d": 0.340911865, "p": 77, "v": 91}], "pos": 1.0, "size": 1.0, "_time": 93.734375}, {"$id": 336, "sounds": [{"d": 0.348014832, "p": 61, "v": 71}, {"d": 0.348014832, "p": 65, "v": 77}], "pos": -2.0, "size": 1.30000007, "_time": 94.078125}, {"$id": 337, "sounds": [{"d": 0.340911865, "p": 70, "v": 80}], "size": 1.0, "_time": 94.08203, "pos": 0}, {"$id": 338, "sounds": [{"d": 0.220169067, "p": 73, "v": 92}], "pos": 1.0, "size": 1.0, "_time": 94.42578}, {"$id": 339, "sounds": [{"d": 0.461647034, "p": 72, "v": 77}], "pos": -1.0, "size": 1.0, "_time": 94.64453}, {"$id": 340, "sounds": [{"d": 0.2130661, "p": 73, "v": 88}], "size": 1.0, "_time": 95.10547, "pos": 0}, {"$id": 341, "sounds": [{"d": 0.127838135, "p": 73, "v": 87}], "size": 1.0, "_time": 95.32031, "pos": 0}, {"$id": 342, "sounds": [{"d": 0.198860168, "p": 80, "v": 90}], "pos": 2.0, "size": 1.0, "_time": 95.453125}, {"$id": 343, "sounds": [{"d": 0.127838135, "p": 79, "v": 92}], "pos": 1.0, "size": 1.0, "_time": 95.65234}, {"$id": 344, "sounds": [{"d": 0.2130661, "p": 49, "v": 67}, {"d": 0.2130661, "p": 61, "v": 69}], "pos": -2.0, "size": 1.30000007, "_time": 95.78125}, {"$id": 345, "sounds": [{"d": 0.348014832, "p": 77, "v": 93}], "size": 1.0, "_time": 95.99609, "pos": 0}, {"$id": 346, "sounds": [{"d": 0.348014832, "p": 72, "v": 93}], "pos": -1.0, "size": 1.0, "_time": 96.34375}, {"$id": 347, "sounds": [{"d": 0.113639832, "p": 72, "v": 93}], "pos": -1.0, "size": 1.0, "_time": 96.69141}, {"$id": 348, "sounds": [{"d": 0.348014832, "p": 65, "v": 79}, {"w": 0.0078125, "d": 0.340911865, "p": 63, "v": 73}, {"w": 0.0078125, "d": 0.340911865, "p": 72, "v": 77}], "pos": -2.0, "size": 1.30000007, "_time": 96.80469}, {"$id": 349, "sounds": [{"d": 0.3338089, "p": 84, "v": 101}], "pos": 2.0, "size": 1.0, "_time": 96.81641}, {"$id": 350, "sounds": [{"d": 0.326705933, "p": 82, "v": 100}], "pos": 1.0, "size": 1.0, "_time": 97.16016}, {"$id": 351, "sounds": [{"d": 0.220169067, "p": 81, "v": 100}], "size": 1.0, "_time": 97.484375, "pos": 0}, {"$id": 352, "sounds": [{"d": 0.1349411, "p": 72, "v": 81}], "pos": -1.0, "size": 1.0, "_time": 97.70703}, {"$id": 353, "sounds": [{"d": 0.326705933, "p": 82, "v": 100}], "pos": 1.0, "size": 1.0, "_time": 97.83984}, {"$id": 354, "sounds": [{"d": 0.340911865, "p": 81, "v": 100}], "size": 1.0, "_time": 98.16797, "pos": 0}, {"$id": 355, "sounds": [{"d": 0.340911865, "p": 77, "v": 81}, {"w": 0.0078125, "d": 0.3338089, "p": 69, "v": 78}], "pos": -2.0, "size": 1.30000007, "_time": 98.16797}, {"$id": 356, "sounds": [{"d": 0.340911865, "p": 82, "v": 100}], "pos": 1.0, "size": 1.0, "_time": 98.50781}, {"$id": 357, "sounds": [{"d": 0.340911865, "p": 70, "v": 78}], "pos": -1.0, "size": 1.30000007, "_time": 98.50781}, {"$id": 358, "sounds": [{"d": 3.07528687, "p": 72, "v": 77}], "size": 1.30000007, "_time": 98.84766, "pos": 0}, {"$id": 359, "sounds": [{"d": 3.068184, "p": 84, "v": 101}], "pos": 2.0, "size": 1.0, "_time": 98.85547}, {"$id": 360, "sounds": [{"d": 0.688919067, "p": 72, "v": 60}], "pos": -1.0, "size": 1.0, "_time": 101.925781}, {"$id": 361, "sounds": [{"d": 0.340911865, "p": 79, "v": 59}], "size": 1.0, "_time": 102.613281, "pos": 0}, {"$id": 362, "sounds": [{"d": 0.539772034, "p": 79, "v": 61}], "size": 1.0, "_time": 102.953125, "pos": 0}, {"$id": 363, "sounds": [{"d": 1.1505661, "p": 81, "v": 58}], "pos": 1.0, "size": 1.0, "_time": 103.496094}, {"$id": 364, "sounds": [{"d": 0.355110168, "p": 72, "v": 50}], "pos": -1.0, "size": 1.0, "_time": 104.644531}, {"$id": 365, "sounds": [{"d": 0.674713135, "p": 79, "v": 62}], "size": 1.0, "_time": 105.0, "pos": 0}, {"$id": 366, "sounds": [{"d": 0.553977966, "p": 79, "v": 60}], "size": 1.0, "_time": 105.675781, "pos": 0}, {"$id": 367, "sounds": [{"d": 1.14346313, "p": 81, "v": 59}], "pos": 1.0, "size": 1.0, "_time": 106.230469}, {"$id": 368, "sounds": [{"d": 0.2130661, "p": 81, "v": 60}], "size": 1.0, "_time": 107.371094, "pos": 0}, {"$id": 369, "sounds": [{"d": 0.142044067, "p": 82, "v": 61}], "pos": 2.0, "size": 1.0, "_time": 107.585938}, {"$id": 370, "sounds": [{"d": 0.3338089, "p": 81, "v": 60}], "size": 1.0, "_time": 107.726563, "pos": 0}, {"$id": 371, "sounds": [{"d": 0.2130661, "p": 77, "v": 61}], "pos": 1.0, "size": 1.0, "_time": 108.0625}, {"$id": 372, "sounds": [{"d": 0.46875, "p": 77, "v": 63}], "pos": 1.0, "size": 1.0, "_time": 108.273438}, {"$id": 373, "sounds": [{"d": 0.205963135, "p": 77, "v": 62}], "pos": 1.0, "size": 1.0, "_time": 108.742188}, {"$id": 374, "sounds": [{"d": 0.127838135, "p": 74, "v": 58}], "pos": -1.0, "size": 1.0, "_time": 108.949219}, {"$id": 375, "sounds": [{"d": 0.220169067, "p": 79, "v": 59}], "pos": 1.0, "size": 1.0, "_time": 109.078125}, {"$id": 376, "sounds": [{"d": 0.6818161, "p": 81, "v": 57}], "pos": 2.0, "size": 1.0, "_time": 109.296875}, {"$id": 377, "sounds": [{"d": 0.127838135, "p": 72, "v": 60}], "pos": -2.0, "size": 1.0, "_time": 109.980469}, {"$id": 378, "sounds": [{"d": 0.220169067, "p": 81, "v": 60}], "size": 1.0, "_time": 110.105469, "pos": 0}, {"$id": 379, "sounds": [{"d": 0.113639832, "p": 82, "v": 62}], "pos": 2.0, "size": 1.0, "_time": 110.328125}, {"$id": 380, "sounds": [{"d": 0.340911865, "p": 81, "v": 60}], "size": 1.0, "_time": 110.441406, "pos": 0}, {"$id": 381, "sounds": [{"d": 0.220169067, "p": 77, "v": 63}], "pos": 1.0, "size": 1.0, "_time": 110.78125}, {"$id": 382, "sounds": [{"d": 0.3338089, "p": 77, "v": 60}], "pos": 1.0, "size": 1.0, "_time": 111.0}, {"$id": 383, "sounds": [{"d": 0.142044067, "p": 74, "v": 58}], "size": 1.0, "_time": 111.335938, "pos": 0}, {"$id": 384, "sounds": [{"d": 0.205963135, "p": 74, "v": 62}], "size": 1.0, "_time": 111.476563, "pos": 0}, {"$id": 385, "sounds": [{"d": 0.3338089, "p": 74, "v": 59}], "size": 1.0, "_time": 111.683594, "pos": 0}, {"$id": 386, "sounds": [{"d": 0.816764832, "p": 72, "v": 58}], "pos": -1.0, "size": 1.0, "_time": 112.015625}, {"$id": 387, "sounds": [{"d": 0.3338089, "p": 72, "v": 67}], "pos": -1.0, "size": 1.0, "_time": 112.832031}, {"$id": 388, "sounds": [{"d": 0.6818161, "p": 65, "v": 70}, {"w": 0.0078125, "d": 0.674713135, "p": 67, "v": 71}], "pos": -2.0, "size": 1.30000007, "_time": 113.167969}, {"$id": 389, "sounds": [{"d": 0.674713135, "p": 79, "v": 81}], "size": 1.0, "_time": 113.175781, "pos": 0}, {"$id": 390, "sounds": [{"d": 0.561080933, "p": 79, "v": 83}], "size": 1.0, "_time": 113.847656, "pos": 0}, {"$id": 391, "sounds": [{"d": 0.46875, "p": 81, "v": 78}], "pos": 1.0, "size": 1.0, "_time": 114.410156}, {"$id": 392, "sounds": [{"d": 0.3338089, "p": 53, "v": 72}], "pos": -2.0, "size": 1.0, "_time": 114.878906}, {"$id": 393, "sounds": [{"d": 0.348014832, "p": 77, "v": 78}], "pos": 2.0, "size": 1.0, "_time": 115.214844}, {"$id": 394, "sounds": [{"d": 0.3338089, "p": 69, "v": 77}], "pos": -1.0, "size": 1.0, "_time": 115.226563}, {"$id": 395, "sounds": [{"d": 0.3338089, "p": 72, "v": 91}], "size": 1.0, "_time": 115.5625, "pos": 0}, {"$id": 396, "sounds": [{"d": 0.553977966, "p": 79, "v": 88}], "pos": 1.0, "size": 1.0, "_time": 115.894531}, {"$id": 397, "sounds": [{"d": 0.546875, "p": 67, "v": 81}, {"d": 0.546875, "p": 72, "v": 78}, {"d": 0.546875, "p": 75, "v": 78}], "pos": -1.0, "size": 1.30000007, "_time": 115.902344}, {"$id": 398, "sounds": [{"d": 0.461647034, "p": 84, "v": 100}], "pos": 2.0, "size": 1.0, "_time": 116.464844}, {"$id": 399, "sounds": [{"d": 0.674713135, "p": 81, "v": 92}], "pos": 1.0, "size": 1.0, "_time": 116.925781}, {"$id": 400, "sounds": [{"d": 0.674713135, "p": 74, "v": 78}, {"w": 0.0078125, "d": 0.667610168, "p": 66, "v": 78}], "pos": -2.0, "size": 1.30000007, "_time": 116.925781}, {"$id": 401, "sounds": [{"d": 0.2130661, "p": 81, "v": 88}], "size": 1.0, "_time": 118.289063, "pos": 0}, {"$id": 402, "sounds": [{"d": 0.120735168, "p": 82, "v": 91}], "pos": 2.0, "size": 1.0, "_time": 118.5}, {"$id": 403, "sounds": [{"d": 0.340911865, "p": 81, "v": 89}], "pos": 1.0, "size": 1.0, "_time": 118.621094}, {"$id": 404, "sounds": [{"d": 0.3338089, "p": 65, "v": 79}, {"w": 0.0078125, "d": 0.326705933, "p": 69, "v": 80}], "pos": -1.0, "size": 1.30000007, "_time": 118.628906}, {"$id": 405, "sounds": [{"d": 0.220169067, "p": 77, "v": 88}], "pos": 1.0, "size": 1.0, "_time": 118.964844}, {"$id": 406, "sounds": [{"d": 0.127838135, "p": 77, "v": 89}], "pos": 1.0, "size": 1.0, "_time": 119.183594}, {"$id": 407, "sounds": [{"d": 0.3338089, "p": 72, "v": 78}], "pos": -1.0, "size": 1.0, "_time": 119.3125}, {"$id": 408, "sounds": [{"d": 0.220169067, "p": 74, "v": 91}], "size": 1.0, "_time": 119.644531, "pos": 0}, {"$id": 409, "sounds": [{"d": 0.127838135, "p": 79, "v": 87}], "pos": 1.0, "size": 1.0, "_time": 119.863281}, {"$id": 410, "sounds": [{"d": 0.220169067, "p": 57, "v": 70}, {"d": 0.220169067, "p": 67, "v": 80}], "pos": -1.0, "size": 1.30000007, "_time": 119.992188}, {"$id": 411, "sounds": [{"d": 0.461647034, "p": 81, "v": 89}], "pos": 2.0, "size": 1.0, "_time": 120.214844}, {"$id": 412, "sounds": [{"d": 0.120735168, "p": 81, "v": 90}], "pos": -1.0, "size": 1.0, "_time": 120.886719}, {"$id": 413, "sounds": [{"d": 0.340911865, "p": 81, "v": 91}], "pos": -1.0, "size": 1.0, "_time": 121.007813}, {"$id": 414, "sounds": [{"d": 0.348014832, "p": 65, "v": 78}, {"d": 0.348014832, "p": 70, "v": 83}], "pos": -2.0, "size": 1.30000007, "_time": 121.347656}, {"$id": 415, "sounds": [{"d": 0.340911865, "p": 82, "v": 100}], "pos": 1.0, "size": 1.0, "_time": 121.355469}, {"$id": 416, "sounds": [{"d": 0.205963135, "p": 81, "v": 100}], "pos": -1.0, "size": 1.0, "_time": 121.699219}, {"$id": 417, "sounds": [{"d": 0.127845764, "p": 82, "v": 100}], "pos": 1.0, "size": 1.0, "_time": 121.902344}, {"$id": 418, "sounds": [{"d": 0.113639832, "p": 82, "v": 100}], "size": 1.0, "_time": 122.257813, "pos": 0}, {"$id": 419, "sounds": [{"d": 0.220169067, "p": 86, "v": 101}], "pos": 2.0, "size": 1.0, "_time": 122.371094}, {"$id": 420, "sounds": [{"d": 0.1349411, "p": 72, "v": 82}, {"w": 0.00390625, "d": 0.127838135, "p": 77, "v": 81}], "pos": -1.0, "size": 1.30000007, "_time": 122.59375}, {"$id": 421, "sounds": [{"d": 0.326705933, "p": 84, "v": 101}], "pos": 1.0, "size": 1.0, "_time": 122.726563}, {"$id": 422, "sounds": [{"d": 0.553977966, "p": 78, "v": 78}], "size": 1.0, "_time": 123.054688, "pos": 0}, {"$id": 423, "sounds": [{"d": 0.553977966, "p": 66, "v": 80}, {"d": 0.553977966, "p": 71, "v": 78}, {"w": 0.0078125, "d": 0.546875, "p": 61, "v": 80}], "pos": -2.0, "size": 1.30000007, "_time": 123.054688}, {"$id": 424, "sounds": [{"d": 0.340911865, "p": 73, "v": 88}], "pos": -1.0, "size": 1.0, "_time": 123.734375}, {"$id": 425, "sounds": [{"d": 0.674713135, "p": 80, "v": 100}], "size": 1.0, "_time": 124.082031, "pos": 0}, {"$id": 426, "sounds": [{"d": 0.667610168, "p": 66, "v": 81}, {"d": 0.667610168, "p": 68, "v": 80}], "pos": -2.0, "size": 1.30000007, "_time": 124.089844}, {"$id": 427, "sounds": [{"d": 0.553977966, "p": 80, "v": 100}], "size": 1.0, "_time": 124.757813, "pos": 0}, {"$id": 428, "sounds": [{"d": 0.46875, "p": 82, "v": 100}], "pos": 1.0, "size": 1.0, "_time": 125.3125}, {"$id": 429, "sounds": [{"d": 0.340911865, "p": 54, "v": 70}], "pos": -2.0, "size": 1.0, "_time": 125.78125}, {"$id": 430, "sounds": [{"d": 0.348014832, "p": 70, "v": 81}], "pos": -1.0, "size": 1.0, "_time": 126.121094}, {"$id": 431, "sounds": [{"d": 0.3338089, "p": 78, "v": 78}], "size": 1.0, "_time": 126.46875, "pos": 0}, {"$id": 432, "sounds": [{"d": 0.6818161, "p": 68, "v": 81}, {"d": 0.6818161, "p": 77, "v": 82}], "pos": -2.0, "size": 1.30000007, "_time": 126.804688}, {"$id": 433, "sounds": [{"d": 0.6818161, "p": 80, "v": 100}], "pos": 1.0, "size": 1.0, "_time": 126.804688}, {"$id": 434, "sounds": [{"d": 0.546875, "p": 80, "v": 100}], "size": 1.0, "_time": 127.492188, "pos": 0}, {"$id": 435, "sounds": [{"d": 0.461654663, "p": 82, "v": 100}], "pos": 1.0, "size": 1.0, "_time": 128.054688}, {"$id": 436, "sounds": [{"d": 0.21307373, "p": 82, "v": 100}], "size": 1.0, "_time": 129.199219, "pos": 0}, {"$id": 437, "sounds": [{"d": 0.1207428, "p": 83, "v": 100}], "pos": 2.0, "size": 1.0, "_time": 129.410156}, {"$id": 438, "sounds": [{"d": 0.3480072, "p": 70, "v": 80}, {"w": 0.0078125, "d": 0.340911865, "p": 66, "v": 82}], "pos": -1.0, "size": 1.30000007, "_time": 129.53125}, {"$id": 439, "sounds": [{"d": 0.340911865, "p": 82, "v": 100}], "pos": 1.0, "size": 1.0, "_time": 129.539063}, {"$id": 440, "sounds": [{"d": 0.220169067, "p": 78, "v": 88}], "pos": 1.0, "size": 1.0, "_time": 129.8789}, {"$id": 441, "sounds": [{"d": 0.127838135, "p": 78, "v": 89}], "pos": 1.0, "size": 1.0, "_time": 130.097656}, {"$id": 442, "sounds": [{"d": 0.326705933, "p": 73, "v": 82}], "pos": -1.0, "size": 1.0, "_time": 130.226563}, {"$id": 443, "sounds": [{"d": 0.220169067, "p": 78, "v": 91}], "pos": 1.0, "size": 1.0, "_time": 130.554688}, {"$id": 444, "sounds": [{"d": 0.1207428, "p": 75, "v": 87}], "size": 1.0, "_time": 130.773438, "pos": 0}, {"$id": 445, "sounds": [{"d": 0.213058472, "p": 80, "v": 90}], "pos": 1.0, "size": 1.0, "_time": 130.894531}, {"$id": 446, "sounds": [{"d": 0.213058472, "p": 68, "v": 81}, {"w": 0.0078125, "d": 0.205963135, "p": 73, "v": 77}], "pos": -1.0, "size": 1.30000007, "_time": 130.894531}, {"$id": 447, "sounds": [{"d": 0.475845337, "p": 82, "v": 100}], "pos": 2.0, "size": 1.0, "_time": 131.109375}, {"$id": 448, "sounds": [{"d": 0.13494873, "p": 73, "v": 92}], "pos": -2.0, "size": 1.0, "_time": 131.789063}, {"$id": 449, "sounds": [{"d": 0.205963135, "p": 82, "v": 100}], "size": 1.0, "_time": 131.925781, "pos": 0}, {"$id": 450, "sounds": [{"d": 0.13494873, "p": 83, "v": 100}], "pos": 2.0, "size": 1.0, "_time": 132.1289}, {"$id": 451, "sounds": [{"d": 0.3408966, "p": 66, "v": 78}], "pos": -1.0, "size": 1.30000007, "_time": 132.265625}, {"$id": 452, "sounds": [{"d": 0.33380127, "p": 82, "v": 100}], "pos": 1.0, "size": 1.0, "_time": 132.273438}, {"$id": 453, "sounds": [{"d": 0.21307373, "p": 78, "v": 87}], "pos": 1.0, "size": 1.0, "_time": 132.605469}, {"$id": 454, "sounds": [{"d": 0.127838135, "p": 78, "v": 88}], "pos": 1.0, "size": 1.0, "_time": 132.820313}, {"$id": 455, "sounds": [{"d": 0.21307373, "p": 70, "v": 83}], "pos": -1.0, "size": 1.0, "_time": 132.949219}, {"$id": 456, "sounds": [{"d": 0.127838135, "p": 75, "v": 88}], "size": 1.0, "_time": 133.160156, "pos": 0}, {"$id": 457, "sounds": [{"d": 0.21307373, "p": 75, "v": 88}], "size": 1.0, "_time": 133.289063, "pos": 0}, {"$id": 458, "sounds": [{"d": 0.1207428, "p": 75, "v": 93}], "size": 1.0, "_time": 133.5, "pos": 0}, {"$id": 459, "sounds": [{"d": 0.21307373, "p": 68, "v": 80}], "pos": -1.0, "size": 1.30000007, "_time": 133.6289}, {"$id": 460, "sounds": [{"d": 0.127838135, "p": 73, "v": 90}], "size": 1.0, "_time": 133.84375, "pos": 0}, {"$id": 461, "sounds": [{"d": 0.561080933, "p": 71, "v": 79}], "pos": -2.0, "size": 1.0, "_time": 133.96875}, {"$id": 462, "sounds": [{"d": 0.3408966, "p": 85, "v": 68}], "pos": 2.0, "size": 1.0, "_time": 134.644531}, {"$id": 463, "sounds": [{"d": 0.33380127, "p": 73, "v": 92}], "pos": -1.0, "size": 1.0, "_time": 134.652344}, {"$id": 464, "sounds": [{"d": 0.6889038, "p": 80, "v": 100}], "size": 1.0, "_time": 134.984375, "pos": 0}, {"$id": 465, "sounds": [{"d": 0.6889038, "p": 66, "v": 79}, {"w": 0.0078125, "d": 0.6818085, "p": 78, "v": 80}, {"w": 0.015625, "d": 0.674713135, "p": 68, "v": 81}], "pos": -2.0, "size": 1.30000007, "_time": 134.984375}, {"$id": 466, "sounds": [{"d": 0.561080933, "p": 80, "v": 100}], "size": 1.0, "_time": 135.675781, "pos": 0}, {"$id": 467, "sounds": [{"d": 0.461654663, "p": 82, "v": 100}], "pos": 1.0, "size": 1.0, "_time": 136.234375}, {"$id": 468, "sounds": [{"d": 0.340911865, "p": 54, "v": 68}], "pos": -2.0, "size": 1.0, "_time": 136.699219}, {"$id": 469, "sounds": [{"d": 0.340911865, "p": 70, "v": 83}], "pos": -1.0, "size": 1.0, "_time": 137.039063}, {"$id": 470, "sounds": [{"d": 0.340911865, "p": 78, "v": 82}], "size": 1.0, "_time": 137.3789, "pos": 0}, {"$id": 471, "sounds": [{"d": 0.546875, "p": 76, "v": 77}, {"w": 0.0078125, "d": 0.539779663, "p": 73, "v": 78}, {"w": 0.0078125, "d": 0.539779663, "p": 68, "v": 79}], "pos": -1.0, "size": 1.30000007, "_time": 137.71875}, {"$id": 472, "sounds": [{"d": 0.546875, "p": 80, "v": 100}], "pos": 1.0, "size": 1.0, "_time": 137.71875}, {"$id": 473, "sounds": [{"d": 0.461654663, "p": 85, "v": 100}], "pos": 2.0, "size": 1.0, "_time": 138.273438}, {"$id": 474, "sounds": [{"d": 0.6889038, "p": 67, "v": 79}, {"w": 0.0078125, "d": 0.6818085, "p": 75, "v": 77}], "pos": -2.0, "size": 1.30000007, "_time": 138.734375}, {"$id": 475, "sounds": [{"d": 0.674713135, "p": 82, "v": 100}], "pos": 1.0, "size": 1.0, "_time": 138.75}, {"$id": 476, "sounds": [{"d": 0.220169067, "p": 82, "v": 100}], "size": 1.0, "_time": 140.105469, "pos": 0}, {"$id": 477, "sounds": [{"d": 0.1136322, "p": 83, "v": 100}], "pos": 2.0, "size": 1.0, "_time": 140.328125}, {"$id": 478, "sounds": [{"d": 0.3480072, "p": 82, "v": 100}], "pos": 1.0, "size": 1.0, "_time": 140.4414}, {"$id": 479, "sounds": [{"d": 0.3480072, "p": 70, "v": 78}, {"d": 0.3480072, "p": 66, "v": 79}], "pos": -1.0, "size": 1.30000007, "_time": 140.4414}, {"$id": 480, "sounds": [{"d": 0.21307373, "p": 78, "v": 91}], "pos": 1.0, "size": 1.0, "_time": 140.789063}, {"$id": 481, "sounds": [{"d": 0.13494873, "p": 78, "v": 87}], "pos": 1.0, "size": 1.0, "_time": 141.0}, {"$id": 482, "sounds": [{"d": 0.1988678, "p": 73, "v": 81}], "pos": -1.0, "size": 1.0, "_time": 141.136719}, {"$id": 483, "sounds": [{"d": 0.3551178, "p": 75, "v": 91}], "size": 1.0, "_time": 141.335938, "pos": 0}, {"$id": 484, "sounds": [{"d": 0.1136322, "p": 80, "v": 90}], "pos": 1.0, "size": 1.0, "_time": 141.6914}, {"$id": 485, "sounds": [{"d": 0.220169067, "p": 68, "v": 83}, {"w": 0.0078125, "d": 0.21307373, "p": 58, "v": 73}], "pos": -1.0, "size": 1.30000007, "_time": 141.804688}, {"$id": 486, "sounds": [{"d": 0.46875, "p": 82, "v": 100}], "pos": 2.0, "size": 1.0, "_time": 142.023438}, {"$id": 487, "sounds": [{"d": 0.127838135, "p": 73, "v": 93}], "pos": -2.0, "size": 1.0, "_time": 142.707031}, {"$id": 488, "sounds": [{"d": 0.220169067, "p": 82, "v": 100}], "size": 1.0, "_time": 142.832031, "pos": 0}, {"$id": 489, "sounds": [{"d": 0.1136322, "p": 83, "v": 100}], "pos": 2.0, "size": 1.0, "_time": 143.054688}, {"$id": 490, "sounds": [{"d": 0.3480072, "p": 70, "v": 80}, {"w": 0.0078125, "d": 0.340911865, "p": 66, "v": 82}], "pos": -1.0, "size": 1.30000007, "_time": 143.167969}, {"$id": 491, "sounds": [{"d": 0.3480072, "p": 82, "v": 100}], "pos": 1.0, "size": 1.0, "_time": 143.167969}, {"$id": 492, "sounds": [{"d": 0.21307373, "p": 78, "v": 93}], "pos": 1.0, "size": 1.0, "_time": 143.515625}, {"$id": 493, "sounds": [{"d": 0.13494873, "p": 78, "v": 91}], "pos": 1.0, "size": 1.0, "_time": 143.730469}, {"$id": 494, "sounds": [{"d": 0.205963135, "p": 73, "v": 81}], "pos": -1.0, "size": 1.0, "_time": 143.863281}, {"$id": 495, "sounds": [{"d": 0.127838135, "p": 75, "v": 87}], "size": 1.0, "_time": 144.070313, "pos": 0}, {"$id": 496, "sounds": [{"d": 0.1207428, "p": 80, "v": 88}], "pos": 1.0, "size": 1.0, "_time": 144.410156}, {"$id": 497, "sounds": [{"d": 0.561080933, "p": 68, "v": 79}], "pos": -1.0, "size": 1.30000007, "_time": 144.539063}, {"$id": 498, "sounds": [{"d": 0.1136322, "p": 82, "v": 100}], "pos": 2.0, "size": 1.0, "_time": 145.097656}, {"$id": 499, "sounds": [{"d": 0.33380127, "p": 70, "v": 79}], "pos": -1.0, "size": 1.30000007, "_time": 145.21875}, {"$id": 500, "sounds": [{"d": 0.33380127, "p": 78, "v": 87}], "pos": 1.0, "size": 1.0, "_time": 145.5625}, {"$id": 501, "sounds": [{"d": 0.3408966, "p": 54, "v": 73}], "pos": -2.0, "size": 1.0, "_time": 145.894531}, {"$id": 502, "sounds": [{"d": 0.33380127, "p": 70, "v": 81}], "size": 1.0, "_time": 145.902344, "pos": 0}, {"$id": 503, "sounds": [{"d": 0.3480072, "p": 61, "v": 79}], "pos": -1.0, "size": 1.0, "_time": 146.234375}, {"$id": 504, "sounds": [{"d": 0.33380127, "p": 73, "v": 82}], "pos": 1.0, "size": 1.0, "_time": 146.582031}, {"$id": 505, "sounds": [{"d": 0.21307373, "p": 66, "v": 82}], "size": 1.0, "_time": 146.917969, "pos": 0}, {"$id": 506, "sounds": [{"d": 0.4616394, "p": 70, "v": 78}], "pos": 1.0, "size": 1.0, "_time": 147.136719}, {"$id": 507, "sounds": [{"d": 0.454544067, "p": 55, "v": 71}], "pos": -1.0, "size": 1.30000007, "_time": 147.144531}, {"$id": 508, "sounds": [{"d": 0.561080933, "p": 55, "v": 70}], "pos": -1.0, "size": 1.30000007, "_time": 147.597656}, {"$id": 509, "sounds": [{"d": 0.561080933, "p": 73, "v": 81}], "pos": 2.0, "size": 1.0, "_time": 147.597656}, {"$id": 510, "sounds": [{"d": 0.1136322, "p": 76, "v": 81}], "pos": -2.0, "size": 1.0, "_time": 148.167969}, {"$id": 511, "sounds": [{"d": 0.21307373, "p": 82, "v": 100}], "size": 1.0, "_time": 148.28125, "pos": 0}, {"$id": 512, "sounds": [{"d": 0.127838135, "p": 83, "v": 100}], "pos": 2.0, "size": 1.0, "_time": 148.4961}, {"$id": 513, "sounds": [{"d": 0.347991943, "p": 66, "v": 78}, {"w": 0.0078125, "d": 0.3408966, "p": 70, "v": 83}], "pos": -1.0, "size": 1.30000007, "_time": 148.6211}, {"$id": 514, "sounds": [{"d": 0.3408966, "p": 82, "v": 100}], "pos": 1.0, "size": 1.0, "_time": 148.6289}, {"$id": 515, "sounds": [{"d": 0.205963135, "p": 78, "v": 88}], "pos": 1.0, "size": 1.0, "_time": 148.96875}, {"$id": 516, "sounds": [{"d": 0.134933472, "p": 78, "v": 92}], "pos": 1.0, "size": 1.0, "_time": 149.175781}, {"$id": 517, "sounds": [{"d": 0.21307373, "p": 75, "v": 87}], "pos": -1.0, "size": 1.0, "_time": 149.644531}, {"$id": 518, "sounds": [{"d": 0.13494873, "p": 80, "v": 92}], "pos": 1.0, "size": 1.0, "_time": 149.859375}, {"$id": 519, "sounds": [{"d": 0.127838135, "p": 82, "v": 100}], "pos": 2.0, "size": 1.0, "_time": 150.214844}, {"$id": 520, "sounds": [{"d": 0.1207428, "p": 82, "v": 100}], "size": 1.0, "_time": 150.886719, "pos": 0}, {"$id": 521, "sounds": [{"d": 0.227279663, "p": 82, "v": 100}], "size": 1.0, "_time": 151.007813, "pos": 0}, {"$id": 522, "sounds": [{"d": 0.1136322, "p": 82, "v": 100}], "size": 1.0, "_time": 151.234375, "pos": 0}, {"$id": 523, "sounds": [{"d": 0.3408966, "p": 83, "v": 100}], "pos": 2.0, "size": 1.0, "_time": 151.347656}, {"$id": 524, "sounds": [{"d": 0.33380127, "p": 73, "v": 78}, {"w": 0.0078125, "d": 0.326705933, "p": 66, "v": 83}], "pos": -1.0, "size": 1.30000007, "_time": 151.355469}, {"$id": 525, "sounds": [{"d": 0.220169067, "p": 82, "v": 100}], "pos": 1.0, "size": 1.0, "_time": 151.699219}, {"$id": 526, "sounds": [{"d": 0.1136322, "p": 78, "v": 88}], "size": 1.0, "_time": 151.917969, "pos": 0}, {"$id": 527, "sounds": [{"d": 0.205963135, "p": 73, "v": 82}], "pos": -1.0, "size": 1.0, "_time": 152.039063}, {"$id": 528, "sounds": [{"d": 0.142044067, "p": 78, "v": 88}], "size": 1.0, "_time": 152.2461, "pos": 0}, {"$id": 529, "sounds": [{"d": 0.319595337, "p": 80, "v": 92}], "pos": 1.0, "size": 1.0, "_time": 152.394531}, {"$id": 530, "sounds": [{"d": 2.24430847, "p": 49, "v": 73}, {"d": 2.24430847, "p": 61, "v": 80}], "pos": -2.0, "size": 1.30000007, "_time": 152.714844}, {"$id": 531, "sounds": [{"d": 2.24430847, "p": 71, "v": 81}, {"w": 0.00390625, "d": 2.23721313, "p": 73, "v": 81}], "pos": 2.0, "size": 1.30000007, "_time": 152.714844}, {"$id": 532, "sounds": [{"d": 0.49005127, "p": 78, "v": 69}], "pos": 1.0, "size": 1.0, "_time": 154.957031}, {"$id": 533, "sounds": [{"d": 1.14346313, "p": 70, "v": 39}, {"d": 1.14346313, "p": 73, "v": 39}], "pos": -1.0, "size": 1.30000007, "_time": 155.449219}, {"$id": 534, "sounds": [{"d": 1.1363678, "p": 78, "v": 67}], "pos": 1.0, "size": 1.0, "_time": 155.453125}, {"$id": 535, "sounds": [{"d": 1.66903687, "p": 76, "v": 42}], "size": 1.0, "_time": 156.589844, "pos": 0}, {"$id": 536, "sounds": [{"d": 1.40623474, "p": 70, "v": 43}, {"w": 0.01171875, "d": 1.39204407, "p": 66, "v": 39}], "pos": -1.0, "size": 1.30000007, "_time": 158.261719}, {"$id": 537, "sounds": [{"d": 1.3991394, "p": 75, "v": 42}], "pos": 1.0, "size": 1.0, "_time": 158.265625}, {"$id": 538, "sounds": [{"d": 0.88067627, "p": 74, "v": 41}], "size": 1.0, "_time": 159.667969, "pos": 0}, {"$id": 539, "sounds": [{"d": 1.81817627, "p": 68, "v": 41}], "pos": -2.0, "size": 1.0, "_time": 160.546875}, {"$id": 540, "sounds": [{"d": 9.445999, "p": 73, "v": 40}, {"w": 0.0078125, "d": 0.007095337, "p": 66, "v": 41}, {"w": 0.0078125, "d": 9.445999, "p": 70, "v": 41}], "pos": -2.0, "size": 1.30000007, "_time": 162.363281}, {"$id": 541, "sounds": [{"d": 9.438904, "p": 78, "v": 41}], "pos": 2.0, "size": 1.0, "_time": 162.3789}], "links": [{"notes": [{"$ref": 43}, {"$ref": 44}]}, {"notes": [{"$ref": 45}, {"$ref": 46}]}, {"notes": [{"$ref": 89}, {"$ref": 90}]}, {"notes": [{"$ref": 91}, {"$ref": 92}]}, {"notes": [{"$ref": 126}, {"$ref": 127}]}, {"notes": [{"$ref": 128}, {"$ref": 129}]}, {"notes": [{"$ref": 144}, {"$ref": 146}]}, {"notes": [{"$ref": 138}, {"$ref": 139}]}]}